pyhexscaffold/__init__.py
pyhexscaffold/main.py
pyhexscaffold/templates/Dockerfile
pyhexscaffold/templates/Makefile
pyhexscaffold/templates/README.md
pyhexscaffold/templates/requirements.txt
pyhexscaffold/templates/scripts/generate_grpc_code.py
pyhexscaffold/templates/src/__init__.py
pyhexscaffold/templates/src/containers.py
pyhexscaffold/templates/src/main.py
pyhexscaffold/templates/src/adapters/__init__.py
pyhexscaffold/templates/src/adapters/api/__init__.py
pyhexscaffold/templates/src/adapters/api/router.py
pyhexscaffold/templates/src/adapters/dtos/__init__.py
pyhexscaffold/templates/src/adapters/events/__init__.py
pyhexscaffold/templates/src/adapters/repository/__init__.py
pyhexscaffold/templates/src/application/__init__.py
pyhexscaffold/templates/src/application/services.py
pyhexscaffold/templates/src/config/__init__.py
pyhexscaffold/templates/src/domain/__init__.py
pyhexscaffold/templates/src/domain/entities.py
pyhexscaffold/templates/src/domain/events.py
pyhexscaffold/templates/src/ports/__init__.py
pyhexscaffold/templates/src/ports/repositories.py
pyhexscaffold/templates/src/ports/services.py
pyhexscaffold/templates/src/proto/service.proto
pyhexscaffold/templates/tests/__init__.py
pyhexscaffold/templates/tests/conftest.py
pyhexscaffold/templates/tests/adapters/test_api.py
pyhexscaffold/templates/tests/application/test_services.py
pyhexscaffold-1.0.5.dist-info/licenses/LICENSE
pyhexscaffold-1.0.5.dist-info/METADATA
pyhexscaffold-1.0.5.dist-info/WHEEL
pyhexscaffold-1.0.5.dist-info/entry_points.txt
pyhexscaffold-1.0.5.dist-info/top_level.txt
pyhexscaffold-1.0.5.dist-info/RECORD
