Metadata-Version: 2.4
Name: pyHexScaffold
Version: 1.0.5
Summary: 六边形架构项目脚手架生成器
Author-email: Ray <ray@rayainfo.cn>
License-Expression: MIT
Project-URL: Homepage, https://github.com/DotNetAge/pyHexScaffold
Project-URL: Bug Tracker, https://github.com/DotNetAge/pyHexScaffold/issues
Keywords: hexagonal,architecture,scaffold,generator,FastAPI
Classifier: Development Status :: 4 - Beta
Classifier: Intended Audience :: Developers
Classifier: Programming Language :: Python :: 3
Classifier: Programming Language :: Python :: 3.8
Classifier: Programming Language :: Python :: 3.9
Classifier: Programming Language :: Python :: 3.10
Classifier: Topic :: Software Development :: Code Generators
Classifier: Topic :: Software Development :: Libraries :: Python Modules
Requires-Python: >=3.8
License-File: LICENSE
Requires-Dist: argparse>=1.4.0
Dynamic: license-file
